{
  "ok": true,
  "videoId": "uJT_V5dS7zA",
  "metadata": {
    "videoId": "uJT_V5dS7zA",
    "title": "일론 머스크는 K-통신사를 위협할 수 있을까? 스타링크 언빡싱&간단사용기!",
    "duration": "16:50",
    "publishDate": "2026-02-18",
    "nativeChapters": []
  },
  "segments": [
    {
      "text": "이놈은 보냈고 이놈은 골체 아프고",
      "startSeconds": 0.04,
      "durationSeconds": 4.68
    },
    {
      "text": "이놈은 일단 모르겠고 넌 날 배신하지",
      "startSeconds": 2.399,
      "durationSeconds": 2.96
    },
    {
      "text": "않을 거지?",
      "startSeconds": 4.72,
      "durationSeconds": 3.88
    },
    {
      "text": ">> 나도 몰라.",
      "startSeconds": 5.359,
      "durationSeconds": 3.241
    },
    {
      "text": "안녕하세요. 이서비입니다. 오늘은",
      "startSeconds": 9.88,
      "durationSeconds": 3.28
    },
    {
      "text": "진짜 저한테 매우 매우 매우 매우",
      "startSeconds": 11.48,
      "durationSeconds": 3.44
    },
    {
      "text": "매우 매우 매우 매우 매우 필요했던",
      "startSeconds": 13.16,
      "durationSeconds": 4.76
    },
    {
      "text": "스타링크를 언박싱하는 날이에요. 아",
      "startSeconds": 14.92,
      "durationSeconds": 5.56
    },
    {
      "text": "스타링크 저는 이게 진짜 필요했던",
      "startSeconds": 17.92,
      "durationSeconds": 4.4
    },
    {
      "text": "이유가 뭐냐면 제가 예전에 한번",
      "startSeconds": 20.48,
      "durationSeconds": 3.719
    },
    {
      "text": "유심을 꼽을 수 있는 공유기를 소개한",
      "startSeconds": 22.32,
      "durationSeconds": 3.64
    },
    {
      "text": "적이 있습니다. 그럴 산 이유도 제가",
      "startSeconds": 24.199,
      "durationSeconds": 3.561
    },
    {
      "text": "레이싱 경기할 때 서킷에서는 우리가",
      "startSeconds": 25.96,
      "durationSeconds": 3.479
    },
    {
      "text": "아스팔트 위에서 수많은 컴퓨터로",
      "startSeconds": 27.76,
      "durationSeconds": 3.2
    },
    {
      "text": "데이터를 실시간으로 봐야 되거든요.",
      "startSeconds": 29.439,
      "durationSeconds": 3.081
    },
    {
      "text": "그렇게 오픈된 공간에서는 와이파이가",
      "startSeconds": 30.96,
      "durationSeconds": 3.48
    },
    {
      "text": "없기 때문에 그런게 필요했었죠. 근데",
      "startSeconds": 32.52,
      "durationSeconds": 3.44
    },
    {
      "text": "막상도 써 보니까 걔가 포지",
      "startSeconds": 34.44,
      "durationSeconds": 3.6
    },
    {
      "text": "기반에다가 너무 느리기도 하고 핸드폰",
      "startSeconds": 35.96,
      "durationSeconds": 3.84
    },
    {
      "text": "테더링처럼 그걸 공유기로 만들어 준",
      "startSeconds": 38.04,
      "durationSeconds": 3.32
    },
    {
      "text": "제품이란 말이에요. 그래서 여러대로",
      "startSeconds": 39.8,
      "durationSeconds": 3.4
    },
    {
      "text": "쓰면 또 많이 버벅이기도 했습니다.",
      "startSeconds": 41.36,
      "durationSeconds": 3.12
    },
    {
      "text": "그래서 작년에 경기를 끝내고 나서",
      "startSeconds": 43.2,
      "durationSeconds": 3.96
    },
    {
      "text": "이제 어떻게 하면 좋을까 하다가 마침",
      "startSeconds": 44.48,
      "durationSeconds": 4.32
    },
    {
      "text": "스타링크 서비스가 시작되었고",
      "startSeconds": 47.16,
      "durationSeconds": 3.399
    },
    {
      "text": "와이파이가 없는 환경에서 다소의",
      "startSeconds": 48.8,
      "durationSeconds": 4.04
    },
    {
      "text": "컴퓨터를 써야 할 상황에서 매우매우",
      "startSeconds": 50.559,
      "durationSeconds": 4
    },
    {
      "text": "좋을 것 같아서 작년 12월 4일",
      "startSeconds": 52.84,
      "durationSeconds": 3.239
    },
    {
      "text": "한국 서비스 런칭을 하자마자",
      "startSeconds": 54.559,
      "durationSeconds": 3.441
    },
    {
      "text": "구입했습니다. 그래서 언박싱 하는",
      "startSeconds": 56.079,
      "durationSeconds": 3.841
    },
    {
      "text": "거는 지금 2월이긴 하지만 12월",
      "startSeconds": 58,
      "durationSeconds": 3.64
    },
    {
      "text": "4일에 구입하고 작년에 도착했던 거",
      "startSeconds": 59.92,
      "durationSeconds": 3.799
    },
    {
      "text": "같아요. 그리고 얘는 택배로 바로",
      "startSeconds": 61.64,
      "durationSeconds": 4.2
    },
    {
      "text": "미국에서 왔습니다. 심지어 스페이스",
      "startSeconds": 63.719,
      "durationSeconds": 3.801
    },
    {
      "text": "X에서 왔어요. 스페이스 X에서.",
      "startSeconds": 65.84,
      "durationSeconds": 3.04
    },
    {
      "text": "그리고이 스타링크라는 거는 우리가",
      "startSeconds": 67.52,
      "durationSeconds": 2.68
    },
    {
      "text": "이제 브랜드명으로 많이 알려져",
      "startSeconds": 68.88,
      "durationSeconds": 3.2
    },
    {
      "text": "있잖아요.이 스타링크 서비스는 실제로",
      "startSeconds": 70.2,
      "durationSeconds": 3.36
    },
    {
      "text": "스페이스 X에서 서비스를 하는",
      "startSeconds": 72.08,
      "durationSeconds": 2.96
    },
    {
      "text": "거예요. 아무튼 이제 스타링크를 쓰기",
      "startSeconds": 73.56,
      "durationSeconds": 3.36
    },
    {
      "text": "위해서는 요렇게 이제 기본적인 베이스",
      "startSeconds": 75.04,
      "durationSeconds": 3.24
    },
    {
      "text": "스테이션이라고 해야 되나? 요거를",
      "startSeconds": 76.92,
      "durationSeconds": 2.68
    },
    {
      "text": "구입해야 됩니다. 그러니까 이제",
      "startSeconds": 78.28,
      "durationSeconds": 2.92
    },
    {
      "text": "수많은 위성이 하늘에 있고 그",
      "startSeconds": 79.6,
      "durationSeconds": 3.68
    },
    {
      "text": "위성이랑 통신을 하기 위한 옛날에",
      "startSeconds": 81.2,
      "durationSeconds": 3.72
    },
    {
      "text": "우리 그 스카이라이프 이런 거 보면",
      "startSeconds": 83.28,
      "durationSeconds": 3.24
    },
    {
      "text": "접시 있잖아요. 그런 것처럼 수발신",
      "startSeconds": 84.92,
      "durationSeconds": 3
    },
    {
      "text": "할 수 있는 그 장비가 필요해요.",
      "startSeconds": 86.52,
      "durationSeconds": 3.239
    },
    {
      "text": "홈페이지에서도 보니까 뭐 미니, 미니",
      "startSeconds": 87.92,
      "durationSeconds": 3.4
    },
    {
      "text": "X 여러 가지 제품들이 엄청",
      "startSeconds": 89.759,
      "durationSeconds": 3.441
    },
    {
      "text": "많았었는데 얘는 이제 스탠더드",
      "startSeconds": 91.32,
      "durationSeconds": 3.6
    },
    {
      "text": "3세대라는 모델입니다. 한국에서",
      "startSeconds": 93.2,
      "durationSeconds": 3.559
    },
    {
      "text": "아직까지 얘만 팔고 있나 보더라고요.",
      "startSeconds": 94.92,
      "durationSeconds": 4.04
    },
    {
      "text": "그리고 얘가 초기 하드웨어 구가가",
      "startSeconds": 96.759,
      "durationSeconds": 4.64
    },
    {
      "text": "조금 비싸요. 거의 한 55만 원",
      "startSeconds": 98.96,
      "durationSeconds": 4.88
    },
    {
      "text": "줬나? 생각보다 꽤 비쌉니다. 우리가",
      "startSeconds": 101.399,
      "durationSeconds": 4.161
    },
    {
      "text": "한국에서 인터넷을 개통하면 50만",
      "startSeconds": 103.84,
      "durationSeconds": 3.8
    },
    {
      "text": "원을 받아도 모질한데 얘는 오히려",
      "startSeconds": 105.56,
      "durationSeconds": 3.8
    },
    {
      "text": "50만 원을 더 내야 돼요. 아,",
      "startSeconds": 107.64,
      "durationSeconds": 4.24
    },
    {
      "text": "뜯기 힘들다. 뭐야 이거? 제대로 안",
      "startSeconds": 109.36,
      "durationSeconds": 4.119
    },
    {
      "text": "뜯기는데.",
      "startSeconds": 111.88,
      "durationSeconds": 5
    },
    {
      "text": "어? 뭐야?이야",
      "startSeconds": 113.479,
      "durationSeconds": 3.401
    },
    {
      "text": "뭐야? 이거 양옆으로 다 뜯어야",
      "startSeconds": 118.399,
      "durationSeconds": 5.36
    },
    {
      "text": "되는데요.",
      "startSeconds": 120.759,
      "durationSeconds": 3
    },
    {
      "text": "양옆으로",
      "startSeconds": 125.28,
      "durationSeconds": 3
    },
    {
      "text": "뜯는게 쉽 쉽지 않네.이야",
      "startSeconds": 131.319,
      "durationSeconds": 4.081
    },
    {
      "text": "떴습니다. 었습니다. 뜯었습니다.",
      "startSeconds": 139,
      "durationSeconds": 4.16
    },
    {
      "text": "뜯어 볼게요. 엄박심 심불하네.",
      "startSeconds": 140.319,
      "durationSeconds": 5
    },
    {
      "text": "아니, 근데 이게 계속이 스타링크",
      "startSeconds": 143.16,
      "durationSeconds": 3.88
    },
    {
      "text": "스페이스엑스 테슬라 일런버스가",
      "startSeconds": 145.319,
      "durationSeconds": 3.481
    },
    {
      "text": "생각나잖아요. 그래서 이제 이것도",
      "startSeconds": 147.04,
      "durationSeconds": 3.279
    },
    {
      "text": "뭔가 전반적인 하드웨어도 약간",
      "startSeconds": 148.8,
      "durationSeconds": 3.12
    },
    {
      "text": "테슬라스러운 느낌이 있어요. 약간",
      "startSeconds": 150.319,
      "durationSeconds": 3.481
    },
    {
      "text": "사이버트럭의 그 각진 느낌이 있기도",
      "startSeconds": 151.92,
      "durationSeconds": 3.599
    },
    {
      "text": "하고 이런 재질 요런게 약간 좀",
      "startSeconds": 153.8,
      "durationSeconds": 4.24
    },
    {
      "text": "테슬라에서 볼 수 있을 것 같은 와,",
      "startSeconds": 155.519,
      "durationSeconds": 4.961
    },
    {
      "text": "크다 커. 그냥 한 27in 정도",
      "startSeconds": 158.04,
      "durationSeconds": 4.119
    },
    {
      "text": "되는 모니터가 하나 있는듯한",
      "startSeconds": 160.48,
      "durationSeconds": 4.2
    },
    {
      "text": "느낌입니다. 그다음에 셋업 관련된",
      "startSeconds": 162.159,
      "durationSeconds": 5.201
    },
    {
      "text": "거랑 설치하는 방식이 그림으로",
      "startSeconds": 164.68,
      "durationSeconds": 5.04
    },
    {
      "text": "있습니다.",
      "startSeconds": 167.36,
      "durationSeconds": 4.2
    },
    {
      "text": "스타링크 앱도 지금 받을게요. 이렇게",
      "startSeconds": 169.72,
      "durationSeconds": 4.239
    },
    {
      "text": "이제 앱 받으면서 볼게요. 스타링크를",
      "startSeconds": 171.56,
      "durationSeconds": 4.92
    },
    {
      "text": "이제 뒷면에 받침대 같은 걸 펴고 아",
      "startSeconds": 173.959,
      "durationSeconds": 4.28
    },
    {
      "text": "이게 06이다. 이게 06이네.",
      "startSeconds": 176.48,
      "durationSeconds": 3.839
    },
    {
      "text": "안테나를 공유기에 연결하고 파워를 또",
      "startSeconds": 178.239,
      "durationSeconds": 3.561
    },
    {
      "text": "공유기에 연결하고 이런 식으로 해서",
      "startSeconds": 180.319,
      "durationSeconds": 3.84
    },
    {
      "text": "케이블을 연결해 주고요. 또 설치가",
      "startSeconds": 181.8,
      "durationSeconds": 4.799
    },
    {
      "text": "좋은 환경이라면 하늘을 뻥 뚫려서",
      "startSeconds": 184.159,
      "durationSeconds": 3.8
    },
    {
      "text": "보고 있어도 됩니다. 장애물이 있으면",
      "startSeconds": 186.599,
      "durationSeconds": 3.2
    },
    {
      "text": "전파 수신이 좀 약할 수 있다 보니까",
      "startSeconds": 187.959,
      "durationSeconds": 4.161
    },
    {
      "text": "이렇게 뭐 어떻게 하면 된다.",
      "startSeconds": 189.799,
      "durationSeconds": 4.601
    },
    {
      "text": "오, 안에도 깔끔하게 잘 돼 있다.",
      "startSeconds": 192.12,
      "durationSeconds": 4.039
    },
    {
      "text": "이건 뭐야? 아, 이게 062이네.",
      "startSeconds": 194.4,
      "durationSeconds": 4.479
    },
    {
      "text": "이게 062. 어, 오, 062에",
      "startSeconds": 196.159,
      "durationSeconds": 4.241
    },
    {
      "text": "렌도 있네. 램포트도 062의",
      "startSeconds": 198.879,
      "durationSeconds": 3.321
    },
    {
      "text": "RJ45. 우리 흔히 볼 수 있는",
      "startSeconds": 200.4,
      "durationSeconds": 5.08
    },
    {
      "text": "램포트도 있습니다. 또 보자. 야,",
      "startSeconds": 202.2,
      "durationSeconds": 5.2
    },
    {
      "text": "케이블 두께하고 이거 장난 아닌데요.",
      "startSeconds": 205.48,
      "durationSeconds": 3.839
    },
    {
      "text": "일반 랜보다 조금 더 두꺼운 거",
      "startSeconds": 207.4,
      "durationSeconds": 3.839
    },
    {
      "text": "같습니다. 그리고 얘가 이제 눈이나",
      "startSeconds": 209.319,
      "durationSeconds": 3.64
    },
    {
      "text": "비 올 때 쓸 수는 있거든요. 물론",
      "startSeconds": 211.239,
      "durationSeconds": 3.321
    },
    {
      "text": "이제 통신 상태가 좋지 않겠지만",
      "startSeconds": 212.959,
      "durationSeconds": 3.241
    },
    {
      "text": "외부에서도 쓸 수 있게 이렇게 실링",
      "startSeconds": 214.56,
      "durationSeconds": 3.16
    },
    {
      "text": "처리가 되어 있어요. 방수를 위해서",
      "startSeconds": 216.2,
      "durationSeconds": 3
    },
    {
      "text": "실링 처리가 되어 있는 거겠죠.",
      "startSeconds": 217.72,
      "durationSeconds": 4
    },
    {
      "text": "그리고 이제요 RG45 랭커 부분 또",
      "startSeconds": 219.2,
      "durationSeconds": 4.2
    },
    {
      "text": "금속으로 되게 좋게 만들었습니다.",
      "startSeconds": 221.72,
      "durationSeconds": 4.48
    },
    {
      "text": "그리고 파워 케이블도 한국 플러그에",
      "startSeconds": 223.4,
      "durationSeconds": 4.68
    },
    {
      "text": "맞게 주고요. 이것 이게 파워",
      "startSeconds": 226.2,
      "durationSeconds": 3.92
    },
    {
      "text": "어댑트네. 게이밍 노트북 보면 전력을",
      "startSeconds": 228.08,
      "durationSeconds": 3.48
    },
    {
      "text": "많이 먹어서 파워 어댑터가 크잖아요.",
      "startSeconds": 230.12,
      "durationSeconds": 3.199
    },
    {
      "text": "그런 것처럼 얘도 있습니다. 얘 같은",
      "startSeconds": 231.56,
      "durationSeconds": 4.2
    },
    {
      "text": "경우에는 195W 출력되고 IP",
      "startSeconds": 233.319,
      "durationSeconds": 4.2
    },
    {
      "text": "66등급 타이퍼라고 되어 있어요.",
      "startSeconds": 235.76,
      "durationSeconds": 3.24
    },
    {
      "text": "그러니까 어느 정도 방수가 되긴 되는",
      "startSeconds": 237.519,
      "durationSeconds": 2.72
    },
    {
      "text": "거예요. 네. 아무튼 이렇게 있고",
      "startSeconds": 239,
      "durationSeconds": 3.36
    },
    {
      "text": "파워 케이블 연결하는 곳에도 방수가",
      "startSeconds": 240.239,
      "durationSeconds": 5.481
    },
    {
      "text": "되어 있습니다. 음. 오.",
      "startSeconds": 242.36,
      "durationSeconds": 5.4
    },
    {
      "text": "자, 화로를 여기 연결하는 거죠?",
      "startSeconds": 245.72,
      "durationSeconds": 4.04
    },
    {
      "text": "여기 여기도 방수 처리가 다 되어",
      "startSeconds": 247.76,
      "durationSeconds": 3.679
    },
    {
      "text": "있고요. 그다음에 케이블도 연결해",
      "startSeconds": 249.76,
      "durationSeconds": 6.8
    },
    {
      "text": "줄게요. 미리. 네.이 여기 연결하고",
      "startSeconds": 251.439,
      "durationSeconds": 5.121
    },
    {
      "text": "케이블을 연결했습니다. 그리고 나서",
      "startSeconds": 256.6,
      "durationSeconds": 5.319
    },
    {
      "text": "여기 뒤에 케이블을 꽂게요.",
      "startSeconds": 258.84,
      "durationSeconds": 5.919
    },
    {
      "text": "예, 케이블 꽂았습니다. 자, 앱해",
      "startSeconds": 261.919,
      "durationSeconds": 6
    },
    {
      "text": "봅시다. 앱 설정 시작 스탠더드 미니",
      "startSeconds": 264.759,
      "durationSeconds": 5.801
    },
    {
      "text": "퍼포먼스 있는데 스탠더드고요. 최적의",
      "startSeconds": 267.919,
      "durationSeconds": 4.56
    },
    {
      "text": "위치 찾기 전망이 탁 트여 있습니다.",
      "startSeconds": 270.56,
      "durationSeconds": 3.12
    },
    {
      "text": "아, 이게 실내선 안 될 것 같은데",
      "startSeconds": 272.479,
      "durationSeconds": 2.44
    },
    {
      "text": "제가 저기 저기 한번 설치해 볼게요.",
      "startSeconds": 273.68,
      "durationSeconds": 5.72
    },
    {
      "text": "저기 창문에 여기서 그래도 창 창밖",
      "startSeconds": 274.919,
      "durationSeconds": 6.641
    },
    {
      "text": ">> 자 세팅 한번 해 봅시다. 전망이 탁",
      "startSeconds": 279.4,
      "durationSeconds": 3.56
    },
    {
      "text": "튀어져 있지 않지만 일단 이제",
      "startSeconds": 281.56,
      "durationSeconds": 2.56
    },
    {
      "text": "실내에서 한번 테스트를 해 봐야",
      "startSeconds": 282.96,
      "durationSeconds": 3.32
    },
    {
      "text": "되니까 어디에 설치하시겠어요? 실내",
      "startSeconds": 284.12,
      "durationSeconds": 3.68
    },
    {
      "text": "원래 하면 안 되는데 발코니 그냥",
      "startSeconds": 286.28,
      "durationSeconds": 4.44
    },
    {
      "text": "할게. 발코니 아 오 카메라로 이걸",
      "startSeconds": 287.8,
      "durationSeconds": 5.08
    },
    {
      "text": "알려주나 보다. 오 방향을 찾는데도",
      "startSeconds": 290.72,
      "durationSeconds": 4.28
    },
    {
      "text": "사용된다. 개방된 공간 뭐 이렇게",
      "startSeconds": 292.88,
      "durationSeconds": 4.599
    },
    {
      "text": "해서 하고",
      "startSeconds": 295,
      "durationSeconds": 5.479
    },
    {
      "text": "우와",
      "startSeconds": 297.479,
      "durationSeconds": 3
    },
    {
      "text": "와 와 야 씨",
      "startSeconds": 300.84,
      "durationSeconds": 4.88
    },
    {
      "text": "오는",
      "startSeconds": 304.08,
      "durationSeconds": 3.119
    },
    {
      "text": "거 같지 않을까요? 아, 근데 이게",
      "startSeconds": 305.72,
      "durationSeconds": 5.479
    },
    {
      "text": "7선이 안 되나 보다.",
      "startSeconds": 307.199,
      "durationSeconds": 6.56
    },
    {
      "text": "아, 360도로 다 뭐 커버를 해야",
      "startSeconds": 311.199,
      "durationSeconds": 2.801
    },
    {
      "text": "되네.",
      "startSeconds": 313.759,
      "durationSeconds": 1.641
    },
    {
      "text": ">> 아, 그냥 일단은 넘어가 보겠습니다.",
      "startSeconds": 314,
      "durationSeconds": 3.52
    },
    {
      "text": "이제 설치 가이드는 제외하고 그냥",
      "startSeconds": 315.4,
      "durationSeconds": 3.76
    },
    {
      "text": "이제 잘했다 치고 한번 해 볼게요.",
      "startSeconds": 317.52,
      "durationSeconds": 3
    },
    {
      "text": "네, 스타링크가 전에 연결되어",
      "startSeconds": 319.16,
      "durationSeconds": 4.159
    },
    {
      "text": "있습니다. 스타링크 와이파이 연결.",
      "startSeconds": 320.52,
      "durationSeconds": 4.64
    },
    {
      "text": "오, 스타링크 뜬다. 오, 예,",
      "startSeconds": 323.319,
      "durationSeconds": 3.521
    },
    {
      "text": "켜졌어. 켜졌어. 스타링크 보완되지",
      "startSeconds": 325.16,
      "durationSeconds": 4.4
    },
    {
      "text": "않는 네트워크라고 하지만 켜졌고 오",
      "startSeconds": 326.84,
      "durationSeconds": 4.799
    },
    {
      "text": "페어링 성공. 위성 검색 중.",
      "startSeconds": 329.56,
      "durationSeconds": 3.8
    },
    {
      "text": "스링크가 위성을 찾고 있습니다. 하늘",
      "startSeconds": 331.639,
      "durationSeconds": 3.441
    },
    {
      "text": "전체가 잘 보이는지 확인하세요.",
      "startSeconds": 333.36,
      "durationSeconds": 3.36
    },
    {
      "text": "와이파이 설정도 여기서 따로 할 수",
      "startSeconds": 335.08,
      "durationSeconds": 3
    },
    {
      "text": "있나 봐요. 오, 네. 스타링크",
      "startSeconds": 336.72,
      "durationSeconds": 3.56
    },
    {
      "text": "와이파이 이름이랑 비보 설정할 수",
      "startSeconds": 338.08,
      "durationSeconds": 5.92
    },
    {
      "text": "있고 속도 테스트.",
      "startSeconds": 340.28,
      "durationSeconds": 5.24
    },
    {
      "text": "예, 지금 인터넷 연결이 지금 안 돼",
      "startSeconds": 344,
      "durationSeconds": 4.52
    },
    {
      "text": "갖고.",
      "startSeconds": 345.52,
      "durationSeconds": 3
    },
    {
      "text": "야, 오. 야, 진짜 야외에서 사용할",
      "startSeconds": 348.68,
      "durationSeconds": 3.44
    },
    {
      "text": "때 이제 눈 올 수도 있잖아요.",
      "startSeconds": 350.6,
      "durationSeconds": 3.24
    },
    {
      "text": "안테나 열선이 있어서 눈 녹임면 더",
      "startSeconds": 352.12,
      "durationSeconds": 3.359
    },
    {
      "text": "돼요. 수면 모드. 수면 모드 뭐야?",
      "startSeconds": 353.84,
      "durationSeconds": 3.479
    },
    {
      "text": "수면 모드일 때 인터넷 연결을",
      "startSeconds": 355.479,
      "durationSeconds": 3.521
    },
    {
      "text": "제공하지 않으면서 전력을 아끼는 거",
      "startSeconds": 357.319,
      "durationSeconds": 3.88
    },
    {
      "text": "같아요. 자, 일단 위성을 검색하고",
      "startSeconds": 359,
      "durationSeconds": 3.759
    },
    {
      "text": "있어요. 위성. 근데 이게 실내선는",
      "startSeconds": 361.199,
      "durationSeconds": 3
    },
    {
      "text": "딱 봐도 안 되겠네요.요 스타링크",
      "startSeconds": 362.759,
      "durationSeconds": 2.921
    },
    {
      "text": "같은 경우에는 이미 많은 분들이 알고",
      "startSeconds": 364.199,
      "durationSeconds": 2.801
    },
    {
      "text": "있긴 하지만 그래도 한번 다시 보고",
      "startSeconds": 365.68,
      "durationSeconds": 3.519
    },
    {
      "text": "가잖아요. 원래 통신을 하기 위해선",
      "startSeconds": 367,
      "durationSeconds": 4.199
    },
    {
      "text": "케이블을 바닥에 닦깝니다. 바다에선",
      "startSeconds": 369.199,
      "durationSeconds": 3.761
    },
    {
      "text": "해적 케이블을 깔기도 하고 육지에서는",
      "startSeconds": 371.199,
      "durationSeconds": 3.44
    },
    {
      "text": "이제 땅속이 묻으면서 케이블을 다",
      "startSeconds": 372.96,
      "durationSeconds": 3.44
    },
    {
      "text": "깔잖아요. 그렇게 케이블을 깔고 나서",
      "startSeconds": 374.639,
      "durationSeconds": 3.881
    },
    {
      "text": "기지국을 만들고 거기서 통신을 하기",
      "startSeconds": 376.4,
      "durationSeconds": 4.32
    },
    {
      "text": "위해 쏴줬다면 스타링크는 위성 통신",
      "startSeconds": 378.52,
      "durationSeconds": 4.119
    },
    {
      "text": "방식을 사용해요. 스타링크라는 이름",
      "startSeconds": 380.72,
      "durationSeconds": 4.199
    },
    {
      "text": "자체도 이제 별길이 링크 연결이 되어",
      "startSeconds": 382.639,
      "durationSeconds": 3.601
    },
    {
      "text": "있다는 뜻이잖아요. 그런 것과",
      "startSeconds": 384.919,
      "durationSeconds": 2.641
    },
    {
      "text": "비슷하게 얘가 작동을 하는 거죠.",
      "startSeconds": 386.24,
      "durationSeconds": 3.239
    },
    {
      "text": "그럼 기존에 위성 통신이 없었냐?",
      "startSeconds": 387.56,
      "durationSeconds": 3.52
    },
    {
      "text": "당연히 있습니다. 다만 이제 가격이",
      "startSeconds": 389.479,
      "durationSeconds": 3.241
    },
    {
      "text": "비싸기도 하고 속도도 느리다 보니까",
      "startSeconds": 391.08,
      "durationSeconds": 3.8
    },
    {
      "text": "일반 사용자는 사실상 거의 쓸 일이",
      "startSeconds": 392.72,
      "durationSeconds": 4.039
    },
    {
      "text": "없었죠. 딜레이도 있다 보니까 게임",
      "startSeconds": 394.88,
      "durationSeconds": 3.68
    },
    {
      "text": "이런 건 아예 꿈도 꿀 수 없었고요.",
      "startSeconds": 396.759,
      "durationSeconds": 3.681
    },
    {
      "text": "근데 스타링크는 그러한 위성통신의",
      "startSeconds": 398.56,
      "durationSeconds": 3.32
    },
    {
      "text": "단점을 해결하기 위해서 몇 가지",
      "startSeconds": 400.44,
      "durationSeconds": 3.199
    },
    {
      "text": "개선이 있었습니다. 기존 위성통신이",
      "startSeconds": 401.88,
      "durationSeconds": 3.159
    },
    {
      "text": "느린 이유가 뭐냐면 약 한",
      "startSeconds": 403.639,
      "durationSeconds": 3.68
    },
    {
      "text": "36,000km 정도 위에 있거든요.",
      "startSeconds": 405.039,
      "durationSeconds": 4.121
    },
    {
      "text": "물리적으로 지면이랑 거리가 멀기",
      "startSeconds": 407.319,
      "durationSeconds": 3.681
    },
    {
      "text": "때문에 속도가 느렸고요. 또 위성이",
      "startSeconds": 409.16,
      "durationSeconds": 3.52
    },
    {
      "text": "정지계도 있잖아요. 그래서 신호가",
      "startSeconds": 411,
      "durationSeconds": 3.08
    },
    {
      "text": "지면까지 왔다 갔다 하는데",
      "startSeconds": 412.68,
      "durationSeconds": 3
    },
    {
      "text": "7만2,000km 정도를 이동해야",
      "startSeconds": 414.08,
      "durationSeconds": 3.76
    },
    {
      "text": "되다 보니까 딜레이가 한 600m가",
      "startSeconds": 415.68,
      "durationSeconds": 3.639
    },
    {
      "text": "나온다고 해요. 그래서 스테링크는",
      "startSeconds": 417.84,
      "durationSeconds": 3.28
    },
    {
      "text": "속도를 계산하기 위해서 일단 위성의",
      "startSeconds": 419.319,
      "durationSeconds": 3.521
    },
    {
      "text": "개드를 적게도 계략 한 550km",
      "startSeconds": 421.12,
      "durationSeconds": 3.24
    },
    {
      "text": "정도라고 하거든요. 그 정도까지",
      "startSeconds": 422.84,
      "durationSeconds": 3.32
    },
    {
      "text": "낮춰서 속도를 많이 높혔고요. 또 전",
      "startSeconds": 424.36,
      "durationSeconds": 3.519
    },
    {
      "text": "세계 지구를 커버하기 위해 스페이스",
      "startSeconds": 426.16,
      "durationSeconds": 3.52
    },
    {
      "text": "X로 수많은 위상을 쏘면서 커버를 해",
      "startSeconds": 427.879,
      "durationSeconds": 3.481
    },
    {
      "text": "버린 거죠. 공력이 보면 이제 메시로",
      "startSeconds": 429.68,
      "durationSeconds": 3
    },
    {
      "text": "연결되는 거 있잖아요. 그런 것처럼",
      "startSeconds": 431.36,
      "durationSeconds": 3.239
    },
    {
      "text": "이제 레이저로 통신하고 또 안테나도",
      "startSeconds": 432.68,
      "durationSeconds": 3.72
    },
    {
      "text": "자동으로 추적하면서 지금처럼 연결",
      "startSeconds": 434.599,
      "durationSeconds": 3.521
    },
    {
      "text": "최적화라든지 여러 가지를 개선하면서",
      "startSeconds": 436.4,
      "durationSeconds": 3.359
    },
    {
      "text": "기존 위성 통신의 단점을 어느 정도",
      "startSeconds": 438.12,
      "durationSeconds": 3.24
    },
    {
      "text": "해결했습니다. 그러니까 기존에 땅을",
      "startSeconds": 439.759,
      "durationSeconds": 3.481
    },
    {
      "text": "파서 케이블로 묻어서 커버리지를",
      "startSeconds": 441.36,
      "durationSeconds": 3.679
    },
    {
      "text": "넓혔다면 스타링크는 그냥 하늘의",
      "startSeconds": 443.24,
      "durationSeconds": 3.56
    },
    {
      "text": "케이블을 깔아버렸다라고 이해하면 좀",
      "startSeconds": 445.039,
      "durationSeconds": 3.28
    },
    {
      "text": "더 쉬울까요? 대신 스타링크처럼",
      "startSeconds": 446.8,
      "durationSeconds": 3.16
    },
    {
      "text": "위성을 너무 많이 쏟다 보니까 별",
      "startSeconds": 448.319,
      "durationSeconds": 3.361
    },
    {
      "text": "사진 찍으시는 분들은이 위성이 계속",
      "startSeconds": 449.96,
      "durationSeconds": 3.519
    },
    {
      "text": "걸리다 보니까 이슈가 있기도 했었죠.",
      "startSeconds": 451.68,
      "durationSeconds": 3.88
    },
    {
      "text": "근데 또 스타링크가 한국에서 이렇게",
      "startSeconds": 453.479,
      "durationSeconds": 3.921
    },
    {
      "text": "런칭을 했다고 해도 크게 관심이 없는",
      "startSeconds": 455.56,
      "durationSeconds": 3.759
    },
    {
      "text": "이유가 뭐냐면 한국처럼 땅덩어리가",
      "startSeconds": 457.4,
      "durationSeconds": 4.12
    },
    {
      "text": "작은 곳에서는 유선이나 무선이나 거의",
      "startSeconds": 459.319,
      "durationSeconds": 3.56
    },
    {
      "text": "안 터지는 곳이 없을 정도로",
      "startSeconds": 461.52,
      "durationSeconds": 3.04
    },
    {
      "text": "커브리지가 넓고 잘 깔려 있어요.",
      "startSeconds": 462.879,
      "durationSeconds": 3.04
    },
    {
      "text": "대신 이러한 스타링크는 이제",
      "startSeconds": 464.56,
      "durationSeconds": 3.24
    },
    {
      "text": "케이블이나 기지국을 깔 수 없는 것들",
      "startSeconds": 465.919,
      "durationSeconds": 3.84
    },
    {
      "text": "바다 산 오지 같은 곳에서 얘가 매우",
      "startSeconds": 467.8,
      "durationSeconds": 3.6
    },
    {
      "text": "유용한 거예요. 특히 한국이 아니라",
      "startSeconds": 469.759,
      "durationSeconds": 3.361
    },
    {
      "text": "미국처럼 땅덩어리가 매우 넓은",
      "startSeconds": 471.4,
      "durationSeconds": 3.639
    },
    {
      "text": "곳에서는 케이블로 유선을 다 깔려면",
      "startSeconds": 473.12,
      "durationSeconds": 3.519
    },
    {
      "text": "비용이나 효율이 떨어지잖아요. 그런",
      "startSeconds": 475.039,
      "durationSeconds": 3
    },
    {
      "text": "곳에서는 또 스타링크를 많이",
      "startSeconds": 476.639,
      "durationSeconds": 3
    },
    {
      "text": "사용한다고 하더라고요. 가격 같은",
      "startSeconds": 478.039,
      "durationSeconds": 3.201
    },
    {
      "text": "경우에도 위성을 쓴다고 해서 미친",
      "startSeconds": 479.639,
      "durationSeconds": 3.601
    },
    {
      "text": "듯이 비싸진 않습니다. 가장 저렴한게",
      "startSeconds": 481.24,
      "durationSeconds": 3.48
    },
    {
      "text": "주고용 라이트라고 해서 월",
      "startSeconds": 483.24,
      "durationSeconds": 3.16
    },
    {
      "text": "64,000원에 쓸 수 있고 얘는",
      "startSeconds": 484.72,
      "durationSeconds": 3.599
    },
    {
      "text": "대신 이제 피크 시간대 속도 제한이",
      "startSeconds": 486.4,
      "durationSeconds": 3.239
    },
    {
      "text": "좀 걸린다고 해요. 만약에 그 속도",
      "startSeconds": 488.319,
      "durationSeconds": 3.081
    },
    {
      "text": "제한이 안 걸린다면 8만7,000원에",
      "startSeconds": 489.639,
      "durationSeconds": 3.201
    },
    {
      "text": "쓸 수 있고요. 그게 아니라 나는",
      "startSeconds": 491.4,
      "durationSeconds": 3.12
    },
    {
      "text": "고정된 위치가 아니라 뭐 전 세계에",
      "startSeconds": 492.84,
      "durationSeconds": 3.359
    },
    {
      "text": "돌아다니면서 막 인터넷을 쓰거나 한다",
      "startSeconds": 494.52,
      "durationSeconds": 3.359
    },
    {
      "text": "그러면 100기가 쓰는게 월",
      "startSeconds": 496.199,
      "durationSeconds": 3.321
    },
    {
      "text": "7만2,000원이고요. 무지하는",
      "startSeconds": 497.879,
      "durationSeconds": 3.241
    },
    {
      "text": "14만4,000원이라고 합니다. 그럼",
      "startSeconds": 499.52,
      "durationSeconds": 3.44
    },
    {
      "text": "30일 무료 체험도 가능하다고 해요.",
      "startSeconds": 501.12,
      "durationSeconds": 5.24
    },
    {
      "text": "자, 그래서 이제 연결은 하고 있는데",
      "startSeconds": 502.96,
      "durationSeconds": 4.679
    },
    {
      "text": "결과적으로 이걸 하려면 밖에",
      "startSeconds": 506.36,
      "durationSeconds": 3.08
    },
    {
      "text": "나가야겠네. 실내서도 테스트해 보려고",
      "startSeconds": 507.639,
      "durationSeconds": 4.561
    },
    {
      "text": "했었는데 완전 뻥 뚫린 야외에서만",
      "startSeconds": 509.44,
      "durationSeconds": 4.56
    },
    {
      "text": "안테나로 이제 위성이랑 통신을 할 수",
      "startSeconds": 512.2,
      "durationSeconds": 3.48
    },
    {
      "text": "있어 갖고 한강 공원에 놨거든요.",
      "startSeconds": 514,
      "durationSeconds": 3.039
    },
    {
      "text": "그래서 여기서 한번 해 보려고요.",
      "startSeconds": 515.68,
      "durationSeconds": 4.839
    },
    {
      "text": "스타링크 예 들고 왔고요 파워뱅크도",
      "startSeconds": 517.039,
      "durationSeconds": 5.601
    },
    {
      "text": "하나 준비했어요.요 파워뱅크로",
      "startSeconds": 520.519,
      "durationSeconds": 4.801
    },
    {
      "text": "연결해서 야외에서 한번 해보려고",
      "startSeconds": 522.64,
      "durationSeconds": 4.12
    },
    {
      "text": "합니다. 여러분데 가서 테스트해",
      "startSeconds": 525.32,
      "durationSeconds": 4.32
    },
    {
      "text": "보죠. 여기 그 한광원에 뻥 뚫린",
      "startSeconds": 526.76,
      "durationSeconds": 4.48
    },
    {
      "text": "데가 있어요. 여기가 이제 장애물도",
      "startSeconds": 529.64,
      "durationSeconds": 4.4
    },
    {
      "text": "없고 하니까 여기서 해 볼까요?",
      "startSeconds": 531.24,
      "durationSeconds": 4.32
    },
    {
      "text": "아 이거 스타링크 하려고 여기 나온",
      "startSeconds": 534.04,
      "durationSeconds": 3.56
    },
    {
      "text": "사람 처음 나 처음일 거야. 이렇게",
      "startSeconds": 535.56,
      "durationSeconds": 4
    },
    {
      "text": "이렇게 요렇게 하고 얘가",
      "startSeconds": 537.6,
      "durationSeconds": 3.88
    },
    {
      "text": "공6이거든요. 공6기2. 안테나는",
      "startSeconds": 539.56,
      "durationSeconds": 4.32
    },
    {
      "text": "밖에 설치해 두고요. 공기만 끌어와서",
      "startSeconds": 541.48,
      "durationSeconds": 3.64
    },
    {
      "text": "이제 집에 설치하는 거죠. 자,",
      "startSeconds": 543.88,
      "durationSeconds": 3.6
    },
    {
      "text": "공유기도 그냥 근처에 두자. 근처에",
      "startSeconds": 545.12,
      "durationSeconds": 4.48
    },
    {
      "text": "두고. 어, 불 들어왔어. 불",
      "startSeconds": 547.48,
      "durationSeconds": 4.28
    },
    {
      "text": "들어왔어. 불 들어왔어. 자,",
      "startSeconds": 549.6,
      "durationSeconds": 3.919
    },
    {
      "text": "스타링크 앱으로 한번 해 보자.",
      "startSeconds": 551.76,
      "durationSeconds": 3.56
    },
    {
      "text": "스타링크 와이파이 연결해야 돼요.",
      "startSeconds": 553.519,
      "durationSeconds": 5.32
    },
    {
      "text": "공기랑 연결했고",
      "startSeconds": 555.32,
      "durationSeconds": 3.519
    },
    {
      "text": "와이파이 연결했는데 아,",
      "startSeconds": 559.04,
      "durationSeconds": 2.76
    },
    {
      "text": "초기화중이래. 초기화중. 기대되지",
      "startSeconds": 560.279,
      "durationSeconds": 3.081
    },
    {
      "text": "않나요? 오, 위성 검색 중이래.",
      "startSeconds": 561.8,
      "durationSeconds": 3.039
    },
    {
      "text": "위성. 위성. 하늘 전체가 잘",
      "startSeconds": 563.36,
      "durationSeconds": 3.24
    },
    {
      "text": "보이는지 확인하세요. 방향 좀",
      "startSeconds": 564.839,
      "durationSeconds": 4.961
    },
    {
      "text": "계산하네요. 방향 계산 중.",
      "startSeconds": 566.6,
      "durationSeconds": 5.239
    },
    {
      "text": "어, 이거 됐다. 어, 잠깐만.",
      "startSeconds": 569.8,
      "durationSeconds": 4.24
    },
    {
      "text": "스타링크의 방향이 25도 어긋나",
      "startSeconds": 571.839,
      "durationSeconds": 4.68
    },
    {
      "text": "있대요. 정렬해 볼까? 돌려서",
      "startSeconds": 574.04,
      "durationSeconds": 6.16
    },
    {
      "text": "테두리에 맞출. 뭐야?",
      "startSeconds": 576.519,
      "durationSeconds": 6.88
    },
    {
      "text": "오, 질린다. 야씨. 오. 야. 오,",
      "startSeconds": 580.2,
      "durationSeconds": 5.36
    },
    {
      "text": "뭐야?",
      "startSeconds": 583.399,
      "durationSeconds": 5.521
    },
    {
      "text": "어, 됐어, 됐어. 오. 아,",
      "startSeconds": 585.56,
      "durationSeconds": 5.04
    },
    {
      "text": "좋은데. 지금 제가 장애물 보기",
      "startSeconds": 588.92,
      "durationSeconds": 3.8
    },
    {
      "text": "누르니까 지금 딱히 장애물이 없는 거",
      "startSeconds": 590.6,
      "durationSeconds": 3.56
    },
    {
      "text": "같아요, 지금 여기서.",
      "startSeconds": 592.72,
      "durationSeconds": 3.48
    },
    {
      "text": "없고 와이파이가 설정되지 않았다 해서",
      "startSeconds": 594.16,
      "durationSeconds": 5.359
    },
    {
      "text": "와이파이 만들겠습니다.",
      "startSeconds": 596.2,
      "durationSeconds": 3.319
    },
    {
      "text": "공유이 처음에 세팅하는 것처럼",
      "startSeconds": 599.68,
      "durationSeconds": 3.599
    },
    {
      "text": "와이파이 만들래요. 근데 제가 이거를",
      "startSeconds": 600.88,
      "durationSeconds": 4.199
    },
    {
      "text": "살 때 기계는 돈을 이미 줬거든요.",
      "startSeconds": 603.279,
      "durationSeconds": 3.68
    },
    {
      "text": "근데 얘도 이제 핸드폰 쓰는 것처럼",
      "startSeconds": 605.079,
      "durationSeconds": 3.481
    },
    {
      "text": "요금 결제해야 되는데 아직까지 요금",
      "startSeconds": 606.959,
      "durationSeconds": 5.641
    },
    {
      "text": "결제하라고 따로 나오진 않았어요.",
      "startSeconds": 608.56,
      "durationSeconds": 5.959
    },
    {
      "text": "뭐 내 8만7,000원이 결제돼",
      "startSeconds": 612.6,
      "durationSeconds": 3.84
    },
    {
      "text": "있네. 8만7,000원짜리면",
      "startSeconds": 614.519,
      "durationSeconds": 4.32
    },
    {
      "text": "아 주거용 프리패스로 결제가 이미",
      "startSeconds": 616.44,
      "durationSeconds": 4.24
    },
    {
      "text": "되어 있으니까 잘 되는 거네요. 아",
      "startSeconds": 618.839,
      "durationSeconds": 3.521
    },
    {
      "text": "난 왠지 처음에 이거 연결하는데",
      "startSeconds": 620.68,
      "durationSeconds": 3.399
    },
    {
      "text": "결제하는 말이 없길래 30일 정도",
      "startSeconds": 622.36,
      "durationSeconds": 3.44
    },
    {
      "text": "공짜로 준다 생각했네요. 와 이거",
      "startSeconds": 624.079,
      "durationSeconds": 3.961
    },
    {
      "text": "제가 보니까 미국에서는 테슬라 위에가",
      "startSeconds": 625.8,
      "durationSeconds": 4.56
    },
    {
      "text": "다 유리잖아요. 거기에 얘는 스타링크",
      "startSeconds": 628.04,
      "durationSeconds": 4.32
    },
    {
      "text": "스탠더드인데 그 미니라는게 있어요.",
      "startSeconds": 630.36,
      "durationSeconds": 3.96
    },
    {
      "text": "미니를 천장에 붙여서 쓰시는 분도",
      "startSeconds": 632.36,
      "durationSeconds": 3.56
    },
    {
      "text": "있더라고요. 오 온라인 됐다. 온라인",
      "startSeconds": 634.32,
      "durationSeconds": 3.24
    },
    {
      "text": "온라인",
      "startSeconds": 635.92,
      "durationSeconds": 3.919
    },
    {
      "text": "통계 와 핑 성공률이 지금 한",
      "startSeconds": 637.56,
      "durationSeconds": 4.079
    },
    {
      "text": "86.4% 4% 지연 시간 또",
      "startSeconds": 639.839,
      "durationSeconds": 4.321
    },
    {
      "text": "나와요. 42ms고 전력 소비가 지금",
      "startSeconds": 641.639,
      "durationSeconds": 4.64
    },
    {
      "text": "34W 정도 됐다고 합니다. 정렬은",
      "startSeconds": 644.16,
      "durationSeconds": 6.88
    },
    {
      "text": "지금 잘 됐고 속도 테스트해 볼까요?",
      "startSeconds": 646.279,
      "durationSeconds": 4.761
    },
    {
      "text": "오드 꽤 그래도 위상 치고는",
      "startSeconds": 654.24,
      "durationSeconds": 4.719
    },
    {
      "text": "빠른데요. 업로드 꽤 빠르다. 50",
      "startSeconds": 657.24,
      "durationSeconds": 3.12
    },
    {
      "text": "50 가까이 나오는데요. 아, 근데",
      "startSeconds": 658.959,
      "durationSeconds": 4.081
    },
    {
      "text": "핑은 지금은 한 45ms가 나옵니다.",
      "startSeconds": 660.36,
      "durationSeconds": 4.2
    },
    {
      "text": "지금 간단하게 이거 속도 측자하면서",
      "startSeconds": 663.04,
      "durationSeconds": 3.2
    },
    {
      "text": "안테나 신호 한번 세 볼까요? 지금은",
      "startSeconds": 664.56,
      "durationSeconds": 3.44
    },
    {
      "text": "또 약간 좀 공유기가 이상적인",
      "startSeconds": 666.24,
      "durationSeconds": 3.44
    },
    {
      "text": "조건이긴 해요. 장애물이랑 벽이랑",
      "startSeconds": 668,
      "durationSeconds": 3.839
    },
    {
      "text": "이렇게 아무것도 없는 상태라 갖고",
      "startSeconds": 669.68,
      "durationSeconds": 4.279
    },
    {
      "text": "이상적인 조건인데 아이폰의 안테나가",
      "startSeconds": 671.839,
      "durationSeconds": 6.161
    },
    {
      "text": "어디까지 떨어지는지 한번 볼게요.",
      "startSeconds": 673.959,
      "durationSeconds": 4.041
    },
    {
      "text": "오 여기서도 아직 안테나가 두",
      "startSeconds": 679.56,
      "durationSeconds": 5.12
    },
    {
      "text": "갠데요. 아 우리 전력도 얼마나",
      "startSeconds": 681.72,
      "durationSeconds": 4.2
    },
    {
      "text": "먹었는지 볼까요? 지금 100%로",
      "startSeconds": 684.68,
      "durationSeconds": 3.44
    },
    {
      "text": "채워왔는데 지금 잠깐 촬영할 때",
      "startSeconds": 685.92,
      "durationSeconds": 4.24
    },
    {
      "text": "썼는데 7% 사용했습니다. 얘",
      "startSeconds": 688.12,
      "durationSeconds": 3.44
    },
    {
      "text": "배터리도 생각보다 용량이 꽤",
      "startSeconds": 690.16,
      "durationSeconds": 2.72
    },
    {
      "text": "되거든요. 자 다시 한번 속도 테스트",
      "startSeconds": 691.56,
      "durationSeconds": 3.64
    },
    {
      "text": "한번 해 보자. 마지막. 오. 아,",
      "startSeconds": 692.88,
      "durationSeconds": 3.92
    },
    {
      "text": "이게 위성 상태에 따라서 속도가 또",
      "startSeconds": 695.2,
      "durationSeconds": 3.079
    },
    {
      "text": "많이 달라지나 봐요. 지금은",
      "startSeconds": 696.8,
      "durationSeconds": 2.4
    },
    {
      "text": "다운로드가 한 300까지",
      "startSeconds": 698.279,
      "durationSeconds": 2.481
    },
    {
      "text": "내려갔습니다. 야, 업로드는 지금",
      "startSeconds": 699.2,
      "durationSeconds": 4.079
    },
    {
      "text": "60에서 7이 나와요. 어, 생각보다",
      "startSeconds": 700.76,
      "durationSeconds": 4.199
    },
    {
      "text": "그래도 꽤 잘 나옵니다. 얘 통신",
      "startSeconds": 703.279,
      "durationSeconds": 3.961
    },
    {
      "text": "보면 스마트폰에 있는 이제 셀로",
      "startSeconds": 704.959,
      "durationSeconds": 3.68
    },
    {
      "text": "통신이랑 비슷한 느낌이거든요. 그",
      "startSeconds": 707.24,
      "durationSeconds": 3.08
    },
    {
      "text": "우리가 유산 인터넷 같은 경우는",
      "startSeconds": 708.639,
      "durationSeconds": 2.841
    },
    {
      "text": "다운로드랑 업로드 속도가",
      "startSeconds": 710.32,
      "durationSeconds": 2.88
    },
    {
      "text": "대칭이잖아요. 근데 아직까지 얘는",
      "startSeconds": 711.48,
      "durationSeconds": 3.039
    },
    {
      "text": "이제 비대칭으로 구성이 되어",
      "startSeconds": 713.2,
      "durationSeconds": 3.199
    },
    {
      "text": "있습니다. 여러 가지 설정들도 되게",
      "startSeconds": 714.519,
      "durationSeconds": 4.32
    },
    {
      "text": "많이 잘 나와요. 컨텐츠 필터링이라고",
      "startSeconds": 716.399,
      "durationSeconds": 4.161
    },
    {
      "text": "나와 있거든요. 제가 듣기로 얘가",
      "startSeconds": 718.839,
      "durationSeconds": 4.081
    },
    {
      "text": "VPN이 기본적으로 내장 된 것처럼",
      "startSeconds": 720.56,
      "durationSeconds": 6.12
    },
    {
      "text": "쓸 수 있다고 했어요. 그래서",
      "startSeconds": 722.92,
      "durationSeconds": 3.76
    },
    {
      "text": "어 진짜네. 포 들어가니까 되는데요.",
      "startSeconds": 727.839,
      "durationSeconds": 7.601
    },
    {
      "text": "와 지금 통계도 핑공률이 아까 86.",
      "startSeconds": 731.92,
      "durationSeconds": 4.919
    },
    {
      "text": "지금 몇 %였잖아요. 지금 한",
      "startSeconds": 735.44,
      "durationSeconds": 3.04
    },
    {
      "text": "98%까지 올라갔습니다. 그것도",
      "startSeconds": 736.839,
      "durationSeconds": 3.24
    },
    {
      "text": "구글이랑 클라우드 플레이어랑 이렇게",
      "startSeconds": 738.48,
      "durationSeconds": 3.159
    },
    {
      "text": "왔다 갔다 하면서 핑 테스트를 하나",
      "startSeconds": 740.079,
      "durationSeconds": 3.601
    },
    {
      "text": "봐요. 지연 시간도 아까 45에서",
      "startSeconds": 741.639,
      "durationSeconds": 3.841
    },
    {
      "text": "지금 한 30 초반 정도까지 되게",
      "startSeconds": 743.68,
      "durationSeconds": 3.599
    },
    {
      "text": "많이 내려왔고 전력 소비 이런 것도",
      "startSeconds": 745.48,
      "durationSeconds": 4.159
    },
    {
      "text": "다 나옵니다. 스피드 테스트에서도",
      "startSeconds": 747.279,
      "durationSeconds": 3.92
    },
    {
      "text": "한번 볼게요. 자체 공유 테스트도",
      "startSeconds": 749.639,
      "durationSeconds": 3.32
    },
    {
      "text": "있지만 여기서도 한번 보겠습니다. 오",
      "startSeconds": 751.199,
      "durationSeconds": 3.521
    },
    {
      "text": "스피드 테스트도 나름 잘 나와요.",
      "startSeconds": 752.959,
      "durationSeconds": 3.201
    },
    {
      "text": "300 이상 나옵니다. 지금 업로드는",
      "startSeconds": 754.72,
      "durationSeconds": 4.08
    },
    {
      "text": "한 20 줄어들었습니다. 핑은 71로",
      "startSeconds": 756.16,
      "durationSeconds": 4.64
    },
    {
      "text": "좀 낮아요. 그러면 이제 이게 궁금할",
      "startSeconds": 758.8,
      "durationSeconds": 3.44
    },
    {
      "text": "수도 있잖아요. 우리 핸드폰에 있던",
      "startSeconds": 760.8,
      "durationSeconds": 3.2
    },
    {
      "text": "일반 속도랑 또 궁금할 수 있으니까",
      "startSeconds": 762.24,
      "durationSeconds": 4.08
    },
    {
      "text": "제가 와이파이를 끊고 일단 5G 먼저",
      "startSeconds": 764,
      "durationSeconds": 4.56
    },
    {
      "text": "테스트를 해 볼게요. 근데 5G는",
      "startSeconds": 766.32,
      "durationSeconds": 4.8
    },
    {
      "text": "확실히 빨라 갖고 스타링크랑은 속도",
      "startSeconds": 768.56,
      "durationSeconds": 4.2
    },
    {
      "text": "차이가 많이 날 거예요. 자, 5G",
      "startSeconds": 771.12,
      "durationSeconds": 3.88
    },
    {
      "text": "했을 때는 이게 상황에 따라 다르지만",
      "startSeconds": 772.76,
      "durationSeconds": 3.68
    },
    {
      "text": "이제 이거보다 더 잘 놓은 케이스가",
      "startSeconds": 775,
      "durationSeconds": 3.16
    },
    {
      "text": "많은데 지금 한 600 bps까지",
      "startSeconds": 776.44,
      "durationSeconds": 3.88
    },
    {
      "text": "나와요. 그리고 업로드는 한 100",
      "startSeconds": 778.16,
      "durationSeconds": 3.72
    },
    {
      "text": "정도 나옵니다. 근데 핑은 확실히",
      "startSeconds": 780.32,
      "durationSeconds": 3.879
    },
    {
      "text": "5자가 좋죠. 그래도 한 24 나오고",
      "startSeconds": 781.88,
      "durationSeconds": 4.84
    },
    {
      "text": "LT도 한번 볼게요. LT도",
      "startSeconds": 784.199,
      "durationSeconds": 4.481
    },
    {
      "text": "어 LT는 한 200 나오는데 200",
      "startSeconds": 786.72,
      "durationSeconds": 3.72
    },
    {
      "text": "거의 LT 속도랑 비슷한 거 같아요.",
      "startSeconds": 788.68,
      "durationSeconds": 3.839
    },
    {
      "text": "LT도 지금 업로드가 한 60 정도",
      "startSeconds": 790.44,
      "durationSeconds": 4.72
    },
    {
      "text": "나온단 말이에요. 핑도 사실 5G나",
      "startSeconds": 792.519,
      "durationSeconds": 4.921
    },
    {
      "text": "LT가 더 빠르긴 해요. 약간 5G의",
      "startSeconds": 795.16,
      "durationSeconds": 5.16
    },
    {
      "text": "한 절반 속도라고 보면 될까요?",
      "startSeconds": 797.44,
      "durationSeconds": 4.8
    },
    {
      "text": "게임 돌려 볼까요? 아이 그래도",
      "startSeconds": 800.32,
      "durationSeconds": 4.36
    },
    {
      "text": "우리가 또 이거 했는데이 핑으로 게임",
      "startSeconds": 802.24,
      "durationSeconds": 5
    },
    {
      "text": "할 수 있는지 한번 봅시다. 안테나는",
      "startSeconds": 804.68,
      "durationSeconds": 3.959
    },
    {
      "text": "저 끝에 두고 지금 공격기만 좀",
      "startSeconds": 807.24,
      "durationSeconds": 3.159
    },
    {
      "text": "앞으로 갖고 왔거든요. 롤 정도는 할",
      "startSeconds": 808.639,
      "durationSeconds": 4.481
    },
    {
      "text": "수 있지 않을까?이 이 정도 핑이면",
      "startSeconds": 810.399,
      "durationSeconds": 5.761
    },
    {
      "text": "오 블랙스 스타링크 어 손이 얼어서",
      "startSeconds": 813.12,
      "durationSeconds": 5.32
    },
    {
      "text": "안 쳐줘",
      "startSeconds": 816.16,
      "durationSeconds": 3.88
    },
    {
      "text": "보안. 오 와이파이 지금 상대 좋아.",
      "startSeconds": 818.44,
      "durationSeconds": 3.32
    },
    {
      "text": "요걸로도 한번 테스트해 볼까? 야",
      "startSeconds": 820.04,
      "durationSeconds": 3.56
    },
    {
      "text": "여기 봐. 스페이스 X 스타링크라고",
      "startSeconds": 821.76,
      "durationSeconds": 3.8
    },
    {
      "text": "딱 적혀 있잖아. 이거 속도 볼까?",
      "startSeconds": 823.6,
      "durationSeconds": 4.72
    },
    {
      "text": "다운은 한 300 가까이 나옵니다.",
      "startSeconds": 825.56,
      "durationSeconds": 4.24
    },
    {
      "text": "스마트폰으로 했던 거랑 거의",
      "startSeconds": 828.32,
      "durationSeconds": 5.079
    },
    {
      "text": "비슷해요. 350. 업은",
      "startSeconds": 829.8,
      "durationSeconds": 6.64
    },
    {
      "text": "옵 엄청 느리네 갑자기.",
      "startSeconds": 833.399,
      "durationSeconds": 5.161
    },
    {
      "text": "네. 지금 한 업로드 7로 되게 낮게",
      "startSeconds": 836.44,
      "durationSeconds": 5.12
    },
    {
      "text": "나왔어요.",
      "startSeconds": 838.56,
      "durationSeconds": 3
    },
    {
      "text": "챔피언 메인이지. 무조건",
      "startSeconds": 842.16,
      "durationSeconds": 3.359
    },
    {
      "text": ">> 다른 사람들은 다 여기서 러닝하고",
      "startSeconds": 844,
      "durationSeconds": 1.8
    },
    {
      "text": "있는데",
      "startSeconds": 845.519,
      "durationSeconds": 2.44
    },
    {
      "text": ">> 저도 뭐 일종에 스포츠를 하고 있는",
      "startSeconds": 845.8,
      "durationSeconds": 5.599
    },
    {
      "text": "거죠. 이스포츠라고.",
      "startSeconds": 847.959,
      "durationSeconds": 3.44
    },
    {
      "text": "어, 빠른 빠른데. 야, 지금 근데",
      "startSeconds": 853.72,
      "durationSeconds": 4.96
    },
    {
      "text": "핑 지금 100 막 70°요. 70",
      "startSeconds": 855.839,
      "durationSeconds": 4.201
    },
    {
      "text": "60까지 떨어졌어. 60까지. 근데",
      "startSeconds": 858.68,
      "durationSeconds": 3.279
    },
    {
      "text": "나름 또 할 만한데요. 막 엄청 못",
      "startSeconds": 860.04,
      "durationSeconds": 4.96
    },
    {
      "text": "하겠다 정도는 아닌 거 같아요.",
      "startSeconds": 861.959,
      "durationSeconds": 6.041
    },
    {
      "text": "해가 없는 거 같아.",
      "startSeconds": 865,
      "durationSeconds": 6.32
    },
    {
      "text": ">> 아, 조금은 있는데 약간 그 핑이",
      "startSeconds": 868,
      "durationSeconds": 5.68
    },
    {
      "text": "조금 있다라는 걸 감안하고 하면 할",
      "startSeconds": 871.32,
      "durationSeconds": 5.439
    },
    {
      "text": "만할 것 같은데요.",
      "startSeconds": 873.68,
      "durationSeconds": 5.88
    },
    {
      "text": "어씨, 밀었다.",
      "startSeconds": 876.759,
      "durationSeconds": 6.32
    },
    {
      "text": "어, 얘 왜 이래?",
      "startSeconds": 879.56,
      "durationSeconds": 3.519
    },
    {
      "text": "오, 봤죠?이 정도 핑이로도 할",
      "startSeconds": 883.24,
      "durationSeconds": 4.92
    },
    {
      "text": "만하네.",
      "startSeconds": 885.16,
      "durationSeconds": 3
    },
    {
      "text": "근데 지금 계속 안정적으로 한",
      "startSeconds": 890.199,
      "durationSeconds": 4.041
    },
    {
      "text": "60에서 70 왔다 갔다 하는 거",
      "startSeconds": 892.44,
      "durationSeconds": 3
    },
    {
      "text": "같아. PD 님이 봤을 때 한번 해",
      "startSeconds": 894.24,
      "durationSeconds": 2.519
    },
    {
      "text": "보실래요? 제가 들어 드릴게요.이",
      "startSeconds": 895.44,
      "durationSeconds": 3.36
    },
    {
      "text": "약간 좀 롤 고수 PD 님이 한번",
      "startSeconds": 896.759,
      "durationSeconds": 3.121
    },
    {
      "text": "지연을 봐 주셔도 좋을 것 같아요.",
      "startSeconds": 898.8,
      "durationSeconds": 2.52
    },
    {
      "text": "저는 사실 막 엄청 많이 하는 건",
      "startSeconds": 899.88,
      "durationSeconds": 1.959
    },
    {
      "text": "아니니까.",
      "startSeconds": 901.32,
      "durationSeconds": 2.519
    },
    {
      "text": ">> 다이아 아니에요. 다이아 최 최고",
      "startSeconds": 901.839,
      "durationSeconds": 3.081
    },
    {
      "text": "튀어는 다이아.",
      "startSeconds": 903.839,
      "durationSeconds": 4.081
    },
    {
      "text": ">> 이야씨",
      "startSeconds": 904.92,
      "durationSeconds": 3
    },
    {
      "text": "지금 첫 느낌 어때요? 첫 느낌",
      "startSeconds": 907.959,
      "durationSeconds": 3.481
    },
    {
      "text": ">> 냉기는 좀 무리가 있을 것 같고",
      "startSeconds": 909.44,
      "durationSeconds": 4.399
    },
    {
      "text": "그래도 칼바람 하는 정도로는 괜찮 거",
      "startSeconds": 911.44,
      "durationSeconds": 2.88
    },
    {
      "text": "같은데.",
      "startSeconds": 913.839,
      "durationSeconds": 1.841
    },
    {
      "text": ">> 아까 대표님이랑 마우스 클리어게",
      "startSeconds": 914.32,
      "durationSeconds": 3.319
    },
    {
      "text": "다른데. 아, 저는 손이 열었어.",
      "startSeconds": 915.68,
      "durationSeconds": 4.959
    },
    {
      "text": "손이",
      "startSeconds": 917.639,
      "durationSeconds": 3
    },
    {
      "text": "실금 있긴 있는데 엄청 체감은 안",
      "startSeconds": 926.079,
      "durationSeconds": 2.721
    },
    {
      "text": "되네.",
      "startSeconds": 928.12,
      "durationSeconds": 3.04
    },
    {
      "text": ">> 그러면은 뭐 오지나 뭐 배 위에서도",
      "startSeconds": 928.8,
      "durationSeconds": 3.399
    },
    {
      "text": "롤 하고 싶다 하면은",
      "startSeconds": 931.16,
      "durationSeconds": 2.919
    },
    {
      "text": ">> 아, 그러면 싹는 싹늘. 아, 이렇게",
      "startSeconds": 932.199,
      "durationSeconds": 3.44
    },
    {
      "text": "스타링크를 간단하게 한번 사용해",
      "startSeconds": 934.079,
      "durationSeconds": 3.401
    },
    {
      "text": "봤습니다. 저는 실제로 얘가 필요하기",
      "startSeconds": 935.639,
      "durationSeconds": 3.801
    },
    {
      "text": "때문에 구입을 한 건데 생각 이상으로",
      "startSeconds": 937.48,
      "durationSeconds": 3.839
    },
    {
      "text": "괜찮았던 거 같아요. 우리가 위성통을",
      "startSeconds": 939.44,
      "durationSeconds": 3.959
    },
    {
      "text": "생각하면 그동안 경험을 봤을 때 엄청",
      "startSeconds": 941.319,
      "durationSeconds": 4.121
    },
    {
      "text": "느리다라는 이제 인식이 있었는데 얘를",
      "startSeconds": 943.399,
      "durationSeconds": 3.761
    },
    {
      "text": "사용해 보니까 그래도 이제 LT급의",
      "startSeconds": 945.44,
      "durationSeconds": 3.079
    },
    {
      "text": "속도가 나와주고 제가 이전에",
      "startSeconds": 947.16,
      "durationSeconds": 3.76
    },
    {
      "text": "경기장에서 썼던 그 LT 062보다도",
      "startSeconds": 948.519,
      "durationSeconds": 4.841
    },
    {
      "text": "오히려 더 쾌적했습니다. 걔는 여러",
      "startSeconds": 950.92,
      "durationSeconds": 4.399
    },
    {
      "text": "PC가 붙으면 많이 느려졌거든요.",
      "startSeconds": 953.36,
      "durationSeconds": 4.399
    },
    {
      "text": "근데 사실 인터넷이 잘되는 이제 한국",
      "startSeconds": 955.319,
      "durationSeconds": 4.241
    },
    {
      "text": "같은 환경에서는 대부분 이런",
      "startSeconds": 957.759,
      "durationSeconds": 3.921
    },
    {
      "text": "스타링크가 사실 필요가 없고 오지나",
      "startSeconds": 959.56,
      "durationSeconds": 3.88
    },
    {
      "text": "특수한 상황 뭐 산에서도 이제",
      "startSeconds": 961.68,
      "durationSeconds": 3.48
    },
    {
      "text": "인터넷을 끌어오기 힘든 환경이라면",
      "startSeconds": 963.44,
      "durationSeconds": 3.199
    },
    {
      "text": "나름 괜찮을 것 같아요. 근데 또",
      "startSeconds": 965.16,
      "durationSeconds": 3.119
    },
    {
      "text": "생각해 보니까 실내에서는 또 얘를 못",
      "startSeconds": 966.639,
      "durationSeconds": 3.241
    },
    {
      "text": "쓰고 얘는 야외에서 달아둬야 되다",
      "startSeconds": 968.279,
      "durationSeconds": 3.321
    },
    {
      "text": "보니까 이런 특징을 알고 구입해야",
      "startSeconds": 969.88,
      "durationSeconds": 3.439
    },
    {
      "text": "되지 않을까요? 재난 상황에서도 또",
      "startSeconds": 971.6,
      "durationSeconds": 3.799
    },
    {
      "text": "유용하게 쓰게 뭐냐면 최근에 전쟁이나",
      "startSeconds": 973.319,
      "durationSeconds": 3.76
    },
    {
      "text": "재난 상황에서도 일론머스크가 막",
      "startSeconds": 975.399,
      "durationSeconds": 2.88
    },
    {
      "text": "이거를 막 무료로 스타링크를",
      "startSeconds": 977.079,
      "durationSeconds": 2.88
    },
    {
      "text": "풀어주거나 그런 상황도 있던 걸 보면",
      "startSeconds": 978.279,
      "durationSeconds": 3.081
    },
    {
      "text": "또 그런 것도 좋아요. 아무튼 오늘",
      "startSeconds": 979.959,
      "durationSeconds": 2.921
    },
    {
      "text": "여기까지요. 오늘은 요런 이제",
      "startSeconds": 981.36,
      "durationSeconds": 3.2
    },
    {
      "text": "스타링크 한국의 서비스를 시작해서",
      "startSeconds": 982.88,
      "durationSeconds": 3.8
    },
    {
      "text": "요거를 한번 살펴봤고 다음에 또 이제",
      "startSeconds": 984.56,
      "durationSeconds": 4.24
    },
    {
      "text": "기회가 된다면 제가 실제로 경기장에서",
      "startSeconds": 986.68,
      "durationSeconds": 4.2
    },
    {
      "text": "사용해 본 후기를 또 남겨 보도록",
      "startSeconds": 988.8,
      "durationSeconds": 3.719
    },
    {
      "text": "할게요. 생각보다 괜찮네요. 이게",
      "startSeconds": 990.88,
      "durationSeconds": 3.84
    },
    {
      "text": "보니까 얘는 그냥 간단하게 서비스 안",
      "startSeconds": 992.519,
      "durationSeconds": 3.68
    },
    {
      "text": "쓸 때는 한 달 단위로 되는 거 같아",
      "startSeconds": 994.72,
      "durationSeconds": 5.32
    },
    {
      "text": "갖고 일시 중지 아 안 쓸 때는 비상",
      "startSeconds": 996.199,
      "durationSeconds": 6.241
    },
    {
      "text": "메시지나 이런 것도 무한 저속 데이터",
      "startSeconds": 1000.04,
      "durationSeconds": 4.32
    },
    {
      "text": "포함해서 월 이렇게도 할 수 있고 안",
      "startSeconds": 1002.44,
      "durationSeconds": 3.639
    },
    {
      "text": "쓸 때는",
      "startSeconds": 1004.36,
      "durationSeconds": 4.08
    },
    {
      "text": "서비스 해지하고 쓸 때만 한 달",
      "startSeconds": 1006.079,
      "durationSeconds": 5.281
    },
    {
      "text": "단위로 써도 되겠네요. Yeah.",
      "startSeconds": 1008.44,
      "durationSeconds": 2.92
    }
  ]
}